commandlines/__init__.py
commandlines/exceptions.py
commandlines/library.py
commandlines/settings.py
commandlines-0.4.1.dist-info/DESCRIPTION.rst
commandlines-0.4.1.dist-info/METADATA
commandlines-0.4.1.dist-info/RECORD
commandlines-0.4.1.dist-info/WHEEL
commandlines-0.4.1.dist-info/metadata.json
commandlines-0.4.1.dist-info/top_level.txt
