Metadata-Version: 1.1
Name: commandlines
Version: 0.4.1
Summary: Command line argument to object parsing library for command line application development
Home-page: https://github.com/chrissimpkins/commandlines
Author: Christopher Simpkins
Author-email: chris@sourcefoundry.org
License: MIT license
Keywords: CLI,command line,parser,shell,application,command line application,argument,argument parser
Platform: any
Classifier: Development Status :: 4 - Beta
Classifier: Intended Audience :: Developers
Classifier: Natural Language :: English
Classifier: License :: OSI Approved :: MIT License
Classifier: Operating System :: OS Independent
Classifier: Programming Language :: Python
Classifier: Programming Language :: Python :: 2
Classifier: Programming Language :: Python :: 2.6
Classifier: Programming Language :: Python :: 2.7
Classifier: Programming Language :: Python :: 3
Classifier: Programming Language :: Python :: 3.3
Classifier: Programming Language :: Python :: 3.4
Classifier: Programming Language :: Python :: 3.5
Classifier: Topic :: Software Development :: Libraries :: Python Modules
